Metadata-Version: 1.0
Name: edasimple
Version: 0.3
Summary: Simple exploratory data analysis
Home-page: UNKNOWN
Author: UNKNOWN
Author-email: UNKNOWN
License: UNKNOWN
Platform: UNKNOWN
